{
  "project_info": {
    "project_number": "1073754955949",
    "project_id": "loginform-a135b",
    "storage_bucket": "loginform-a135b.appspot.com"
  },
  "client": [
    {
      "client_info": {
        "mobilesdk_app_id": "1:1073754955949:android:2d782b5269131c05826624",
        "android_client_info": {
          "package_name": "com.example.factory_checksheet"
        }
      },
      "oauth_client": [
        {
          "client_id": "1073754955949-l4hq0fp1eodue258rbfhoukbovsq51r5.apps.googleusercontent.com",
          "client_type": 3
        }
      ],
      "api_key": [
        {
          "current_key": "AIzaSyDxWp4fU9VirVvfK0ZzBXJ2rCRYvI3zqIM"
        }
      ],
      "services": {
        "appinvite_service": {
          "other_platform_oauth_client": [
            {
              "client_id": "1073754955949-l4hq0fp1eodue258rbfhoukbovsq51r5.apps.googleusercontent.com",
              "client_type": 3
            }
          ]
        }
      }
    }
  ],
  "configuration_version": "1"
}